README.rst
setup.cfg
setup.py
accounting/__init__.py
accounting/defaults.py
accounting/urls.py
accounting/wsgi.py
accounting/apps/__init__.py
accounting/apps/context_processors.py
accounting/apps/books/__init__.py
accounting/apps/books/admin.py
accounting/apps/books/apps.py
accounting/apps/books/calculators.py
accounting/apps/books/context_processors.py
accounting/apps/books/forms.py
accounting/apps/books/managers.py
accounting/apps/books/middlewares.py
accounting/apps/books/mixins.py
accounting/apps/books/models.py
accounting/apps/books/urls.py
accounting/apps/books/utils.py
accounting/apps/books/views.py
accounting/apps/books/migrations/0001_initial.py
accounting/apps/books/migrations/0002_auto_20141029_1606.py
accounting/apps/books/migrations/0003_auto_20141029_1606.py
accounting/apps/books/migrations/0004_auto_20141104_1026.py
accounting/apps/books/migrations/0005_auto_20150128_1458.py
accounting/apps/books/migrations/0006_auto_20150206_1836.py
accounting/apps/books/migrations/0007_auto_20150206_1836.py
accounting/apps/books/migrations/0008_auto_20150206_1843.py
accounting/apps/books/migrations/0009_auto_20150206_1850.py
accounting/apps/books/migrations/0010_auto_20150210_1449.py
accounting/apps/books/migrations/0011_auto_20150324_1430.py
accounting/apps/books/migrations/__init__.py
accounting/apps/books/templatetags/__init__.py
accounting/apps/books/templatetags/status_filters.py
accounting/apps/connect/__init__.py
accounting/apps/connect/middlewares.py
accounting/apps/connect/models.py
accounting/apps/connect/steps.py
accounting/apps/connect/urls.py
accounting/apps/connect/views.py
accounting/apps/people/__init__.py
accounting/apps/people/admin.py
accounting/apps/people/forms.py
accounting/apps/people/models.py
accounting/apps/people/urls.py
accounting/apps/people/views.py
accounting/apps/people/migrations/0001_initial.py
accounting/apps/people/migrations/0002_auto_20141029_1609.py
accounting/apps/people/migrations/0003_employee_payroll_tax_rate.py
django_accounting.egg-info/PKG-INFO
django_accounting.egg-info/SOURCES.txt
django_accounting.egg-info/dependency_links.txt
django_accounting.egg-info/pbr.json
django_accounting.egg-info/requires.txt
django_accounting.egg-info/top_level.txt