Metadata-Version: 1.1
Name: django-accounting
Version: 0.2.2
Summary: Accounting made accessible for small businesses and sole proprietorships through a simple Django project
Home-page: https://github.com/dulaccc/django-accounting
Author: Pierre Dulac
Author-email: pierre@dulaccc.me
License: MIT
Keywords: Accounting,Django,Money,Cashflow
Platform: linux
Classifier: Development Status :: 2 - Pre-Alpha
Classifier: Environment :: Web Environment
Classifier: Framework :: Django
Classifier: Intended Audience :: Developers
Classifier: License :: OSI Approved :: MIT License
Classifier: Operating System :: Unix
Classifier: Programming Language :: Python
Classifier: Programming Language :: Python :: 3
Classifier: Programming Language :: Python :: 3.3
Classifier: Programming Language :: Python :: 3.4
Classifier: Topic :: Software Development :: Libraries :: Application Frameworks
